flickr_uploader-2.8.7.data/data/etc/uploadr.cron
flickr_uploader-2.8.7.data/data/etc/uploadr.ini
flickr_uploader-2.8.7.data/scripts/uploadr.py
flickr_uploader-2.8.7.dist-info/METADATA
flickr_uploader-2.8.7.dist-info/RECORD
flickr_uploader-2.8.7.dist-info/WHEEL
flickr_uploader-2.8.7.dist-info/top_level.txt
lib/FlickrApiWrapper.py
lib/FlickrUploadr.py
lib/Konstants.py
lib/MyConfig.py
lib/NicePrint.py
lib/SQLiteDBHelper.py
lib/__init__.py
lib/__version__.py
lib/mprocessing.py
lib/multiprocessing_logging.py
lib/rate_limited.py
