Metadata-Version: 2.1
Name: flickr-uploader
Version: 2.8.7
Summary: Upload a directory of media (pics/videos) to Flickr for showing off your pics on the WEB and as a backup of your local storage. flickr-uploader designed primarly for Synology Devices. Also works on Linux, Mac and Windows systems.
Home-page: https://github.com/oPromessa/flickr-uploader/
Author: oPromessa
Author-email: oPromessa@gmail.com
License: MIT
Platform: UNKNOWN
Classifier: Development Status :: 4 - Beta
Classifier: Intended Audience :: Developers
Classifier: License :: OSI Approved :: MIT License
Classifier: Programming Language :: Python
Classifier: Programming Language :: Python :: 2.7
Classifier: Programming Language :: Python :: 3.6
Classifier: Topic :: Multimedia
Classifier: Topic :: System :: Archiving :: Backup
Classifier: Topic :: System :: Archiving :: Mirroring
Requires-Dist: flickrapi
Requires-Dist: portalocker; platform_system == "Windows"
